{
    "common": {
      "validation": {
        "name": {
          "leadingSpace": "名字不能以空格开头",
          "trailingSpace": "名字不能以空格结尾",
          "tooShort": "名字需要至少两个字符",
          "tooLong": "名字长度过长",
          "containsNumbers": "名字不能包含数字",
          "invalidCharacters": "名字包含无效字符",
          "multipleSpaces": "名字不能包含空格",
          "startsWithSpecial": "名字包含无效字符",
          "endsWithSpecial": "名字包含无效字符"
        },
        "score": {
          "outOfRange": "分数必须在 {min} 到 {max} 之间"
        }
      },

      "navigation": {
        "nextButton": "下一步",
        "previousButton": "上一步",
        "pageIndicator": "Page {current} of {total}"
      }
    },

    "zhongkao": {
      "title": "成都市中考模拟志愿填报",
      "totalPages": 4,
      "pages": {
        "page1": {
          "title": "请输入您的姓名:"
        },
        "page2": {
          "title": "性别:",
          "options": ["女", "男"]
        },
        "scorepage":{
          "title": "请输入您的成绩:",
          "scores": [
            {
              "title": "语文:",
              "range": [0, 150]
            },
            {
              "title": "数学:",
              "range": [0, 150]
            },
            {
              "title": "英语:",
              "range": [0, 150]
            },
            {
              "title": "物理:",
              "range": [0, 70]
            },
            {
              "title": "化学:",
              "range": [0, 50]
            },
            {
              "title": "体育:",
              "range": [0, 60]
            },
            {
              "title": "道法:",
              "range": [8, 12, 16, 20]
            },
            {
              "title": "历史:",
              "range": [8, 12, 16, 20]
            },
            {
              "title": "生物:",
              "range": [8, 12, 16, 20]
            },
            {
              "title": "地理:",
              "range": [8, 12, 16, 20]
            }
          ],
          "totalScore": "总分:"
        },
        "summarypage": {
          "title": "信息确认",
          "nameLabel": "姓名:",
          "genderLabel": "性别:",
          "scoresLabel": "各科成绩:",
          "totalScoreLabel": "总分:"
        }
      }
    }
  }